pyud/__init__.py
pyud/client.py
pyud/definition.py
pyud-1.0.1.dist-info/LICENSE
pyud-1.0.1.dist-info/METADATA
pyud-1.0.1.dist-info/WHEEL
pyud-1.0.1.dist-info/top_level.txt
pyud-1.0.1.dist-info/RECORD
