Metadata-Version: 2.1
Name: pyud
Version: 1.0.1
Summary: A simple wrapper for the Urban Dictionary API
Home-page: https://github.com/WilliamWFLee/pyud
Author: William Lee
Author-email: wlee753159@gmail.com
License: GNU GPL v3.0
Project-URL: Documentation, https://pyud.readthedocs.io
Project-URL: Source, https://github.com/WilliamWFLee/pyud
Keywords: urbandictionary api async
Platform: UNKNOWN
Classifier: Development Status :: 5 - Production/Stable
Classifier: Intended Audience :: Developers
Classifier: License :: OSI Approved :: GNU General Public License v3 or later (GPLv3+)
Classifier: Natural Language :: English
Classifier: Operating System :: OS Independent
Classifier: Programming Language :: Python :: 3 :: Only
Classifier: Programming Language :: Python :: 3.5
Classifier: Programming Language :: Python :: 3.6
Classifier: Programming Language :: Python :: 3.7
Classifier: Programming Language :: Python :: 3.8
Classifier: Topic :: Internet
Classifier: Topic :: Software Development :: Libraries
Classifier: Topic :: Software Development :: Libraries :: Python Modules
Classifier: Topic :: Utilities
Classifier: Typing :: Typed
Requires-Python: ~=3.5.3
Requires-Dist: aiohttp (==3.6.2)
